setup.py
django_log_timings_parser.egg-info/PKG-INFO
django_log_timings_parser.egg-info/SOURCES.txt
django_log_timings_parser.egg-info/dependency_links.txt
django_log_timings_parser.egg-info/requires.txt
django_log_timings_parser.egg-info/top_level.txt
log_timings_parser/__init__.py