Metadata-Version: 1.0
Name: django-log-timings-parser
Version: 1.0.0
Summary: Parses your web server access logs, resolves your URLs against your django project, and tells you what URLs take a long time
Home-page: UNKNOWN
Author: Rory McCann
Author-email: rory@technomancy.org
License: GPLv3
Platform: UNKNOWN
